sql2lineage/__init__.py
sql2lineage/graph.py
sql2lineage/model.py
sql2lineage/parser.py
sql2lineage/utils.py
sql2lineage/types/model.py
sql2lineage/types/parser.py
sql2lineage/types/table.py
sql2lineage/types/utils.py
sql2lineage-0.5.1.dist-info/licenses/LICENSE
sql2lineage-0.5.1.dist-info/METADATA
sql2lineage-0.5.1.dist-info/WHEEL
sql2lineage-0.5.1.dist-info/top_level.txt
sql2lineage-0.5.1.dist-info/RECORD
